ratelimit/__init__.py
ratelimit/decorators.py
ratelimit/exception.py
ratelimit/utils.py
ratelimit_whl_copy-2.2.1.dist-info/LICENSE.txt
ratelimit_whl_copy-2.2.1.dist-info/METADATA
ratelimit_whl_copy-2.2.1.dist-info/WHEEL
ratelimit_whl_copy-2.2.1.dist-info/top_level.txt
ratelimit_whl_copy-2.2.1.dist-info/RECORD
