Metadata-Version: 2.1
Name: ratelimit-whl-copy
Version: 2.2.1
Summary: API rate limit decorator
Home-page: https://github.com/zzzhang72/ratelimit
Author: Chris Zhang
Author-email: zzzhang@uber.com
License: MIT
Keywords: ratelimit,api,decorator
Classifier: Development Status :: 5 - Production/Stable
Classifier: Intended Audience :: Developers
Classifier: License :: OSI Approved :: MIT License
Classifier: Natural Language :: English
Classifier: Programming Language :: Python
Classifier: Topic :: Software Development
License-File: LICENSE.txt
